LICENSE
MANIFEST.in
README
randua.py
setup.py
randua.egg-info/PKG-INFO
randua.egg-info/SOURCES.txt
randua.egg-info/dependency_links.txt
randua.egg-info/entry_points.txt
randua.egg-info/top_level.txt