Metadata-Version: 1.1
Name: randua
Version: 0.0.1
Summary: Random User Agent string generator
Home-page: https://github.com/naglis/randua
Author: Naglis Jonaitis
Author-email: njonaitis@gmail.com
License: UNKNOWN
Keywords: browser,useragent
Platform: UNKNOWN
Classifier: Development Status :: 3 - Alpha
Classifier: License :: Public Domain
Classifier: Environment :: Console
Classifier: Intended Audience :: Developers
Classifier: Operating System :: OS Independent
Classifier: Programming Language :: Python
Classifier: Programming Language :: Python :: 2.7
Classifier: Programming Language :: Python :: 3.3
Classifier: Topic :: Internet :: WWW/HTTP
Classifier: Topic :: Internet :: WWW/HTTP :: Browsers
Classifier: Topic :: Software Development :: Libraries :: Python Modules
